mlmaid/__init__.py
mlmaid/main.py
mlmaid-0.1.2.3.dist-info/LICENSE
mlmaid-0.1.2.3.dist-info/METADATA
mlmaid-0.1.2.3.dist-info/WHEEL
mlmaid-0.1.2.3.dist-info/top_level.txt
mlmaid-0.1.2.3.dist-info/RECORD
