Metadata-Version: 2.1
Name: mlmaid
Version: 0.1.2.3
Summary: ML-MAID : ML - Miniature Automatic Installer for Dependencies
Home-page: https://github.com/xbais/ml-maid
Author: Aakash Singh Bais
Author-email: xbais@duck.com
License-File: LICENSE
Requires-Dist: tqdm
Requires-Dist: setuptools
Requires-Dist: tabulate
Requires-Dist: wheel
